calctree/__init__.py
calctree/calculation_result.py
calctree/client.py
calctree/exceptions.py
calctree-0.2.3.dist-info/LICENSE
calctree-0.2.3.dist-info/METADATA
calctree-0.2.3.dist-info/WHEEL
calctree-0.2.3.dist-info/RECORD
